{"candidate": "                if not left_value == right_value:\n", "entropy": 10.891536304374}
{"candidate": "                if left_value != right_value:\n", "entropy": 12.504544525493001}
{"candidate": "                if left_value != right_value:\n", "entropy": 7.960631718933}
{"candidate": "                if left_value != right_value:\n", "entropy": 3.8795869071545}
{"candidate": "                if left_value != right_value:\n", "entropy": 2.5358801514545}
{"candidate": "                if left_value != right_value:\n", "entropy": 4.428973395493}
{"candidate": "                if left_value != right_value:\n", "entropy": 2.5358801514545}
{"candidate": "                if left_value != right_value:\n", "entropy": 11.141615918932999}
{"candidate": "                if left_value != right_value:\n", "entropy": 2.8947356197145}
{"candidate": "                if left_value != right_value:\n", "entropy": 9.270147705592999}
{"candidate": "                if left_value != right_value:\n", "entropy": 2.536154607793}
{"candidate": "                if left_value != right_value:\n", "entropy": 2.536153627793}
{"candidate": "                if left_value != right_value:\n", "entropy": 9.998773571631501}
{"candidate": "                if left_value != right_value:\n", "entropy": 8.587438086154501}
{"candidate": "                if left_value != right_value:\n", "entropy": 3.5626537073295}
{"candidate": "                if left_value != right_value:\n", "entropy": 9.026145595433}
{"candidate": "                if not (left_value == right_value):\n", "entropy": 7.200443536788001}
{"candidate": "                if left_value != right_value:\n", "entropy": 4.2247538361545}
{"candidate": "                if left_value != right_value:\n", "entropy": 3.5623168361545003}
{"candidate": "                if left_value != right_value:\n", "entropy": 2.536154727893}
