{"project": "sanic", "bug": 2, "project_url": "https://github.com/huge-success/sanic", "file_changed": "sanic/server.py", "buggy_commit_id": "ba9b432993019b0af0c4827a5ed42aaa091bd17d", "fixed_commit_id": "801595e24acdf8050b8d3ffa512d424147848d32", "lines_deleted": {}, "lines_added": {"737": "    def start_serving(self):\n", "738": "        if self.server:\n", "739": "            try:\n", "740": "                return self.server.start_serving()\n", "741": "            except AttributeError:\n", "742": "                raise NotImplementedError(\n", "743": "                    \"server.start_serving not available in this version \"\n", "744": "                    \"of asyncio or uvloop.\"\n", "745": "                )\n", "746": "\n", "747": "    def serve_forever(self):\n", "748": "        if self.server:\n", "749": "            try:\n", "750": "                return self.server.serve_forever()\n", "751": "            except AttributeError:\n", "752": "                raise NotImplementedError(\n", "753": "                    \"server.serve_forever not available in this version \"\n", "754": "                    \"of asyncio or uvloop.\"\n", "755": "                )\n", "756": "\n"}}